powerfit_em/_powerfit.c
powerfit_em/_extensions.c
powerfit_em/_powerfit.pyx
powerfit_em/elements.py
powerfit_em/powerfit.py
powerfit_em/analyzer.py
powerfit_em/__init__.py
powerfit_em/_extensions.cpython-313-darwin.so
powerfit_em/rotations.py
powerfit_em/volume.py
powerfit_em/_powerfit.cpython-313-darwin.so
powerfit_em/structure.py
powerfit_em/shape_descriptor.py
powerfit_em/powerfitter.py
powerfit_em/helpers.py
powerfit_em/report.py
powerfit_em/correlators/cpu.py
powerfit_em/correlators/clkernels.py
powerfit_em/correlators/__init__.py
powerfit_em/correlators/kernels.cl
powerfit_em/correlators/shared.py
powerfit_em/correlators/gpu.py
powerfit_em/data/c48u7111.npy
powerfit_em/data/c600vc.npy
powerfit_em/data/c48u27.npy
powerfit_em/data/c600v.npy
powerfit_em/data/c48u1201.npy
powerfit_em/data/c48u5879.npy
powerfit_em/data/c48u83.npy
powerfit_em/data/E.npy
powerfit_em/data/c48n309.npy
powerfit_em/data/c48n527.npy
powerfit_em/data/c48u2219.npy
powerfit_em/data/c48u1641.npy
powerfit_em/data/c48u181.npy
powerfit_em/data/c48u815.npy
powerfit_em/data/c48u3733.npy
powerfit_em/data/c48n9.npy
powerfit_em/data/c48u2947.npy
powerfit_em/data/c48u1.npy
powerfit_em/data/c48u8649.npy
powerfit_em/data/c48u1153.npy
powerfit_em/data/c48u4749.npy
powerfit_em-4.0.3.dist-info/RECORD
powerfit_em-4.0.3.dist-info/WHEEL
powerfit_em-4.0.3.dist-info/entry_points.txt
powerfit_em-4.0.3.dist-info/top_level.txt
powerfit_em-4.0.3.dist-info/METADATA
powerfit_em-4.0.3.dist-info/licenses/LICENSE
