Metadata-Version: 2.4
Name: powerfit-em
Version: 4.0.3
Summary: Rigid body fitting of high-resolution structures in low-resolution cryo-electron microscopy density maps
Author-email: "Gydo C.P. van Zundert" <g.c.p.vanzundert@uu.nl>
Maintainer: BonvinLab
Maintainer-email: bonvinlab.support@uu.nl
License-Expression: Apache-2.0
Project-URL: issues, https://github.com/haddocking/powerfit
Project-URL: homepage, https://github.com/haddocking/powerfit
Project-URL: source, https://github.com/haddocking/powerfit
Project-URL: tutorial, https://www.bonvinlab.org/education/Others/
Classifier: Development Status :: 3 - Alpha
Classifier: Programming Language :: Python :: 3.10
Classifier: Programming Language :: Python :: 3.11
Classifier: Programming Language :: Python :: 3.12
Classifier: Programming Language :: Python :: 3.13
Classifier: Intended Audience :: Science/Research
Classifier: Topic :: Scientific/Engineering :: Bio-Informatics
Requires-Python: >=3.10
License-File: LICENSE
Requires-Dist: numpy>=1.8
Requires-Dist: pyfftw>=0.12.0; platform_machine != "wasm32" and sys_platform != "darwin"
Requires-Dist: scipy
Requires-Dist: tqdm
Requires-Dist: rich
Requires-Dist: molviewspec>=1.6.0
Provides-Extra: opencl
Requires-Dist: pyopencl; extra == "opencl"
Requires-Dist: siphash24; extra == "opencl"
Requires-Dist: pyvkfft; extra == "opencl"
Provides-Extra: pocl
Requires-Dist: pyopencl[pocl]; extra == "pocl"
Requires-Dist: siphash24; extra == "pocl"
Requires-Dist: pyvkfft; extra == "pocl"
Provides-Extra: dev
Requires-Dist: pytest; extra == "dev"
Requires-Dist: pytest-cov; extra == "dev"
Requires-Dist: ruff; extra == "dev"
Requires-Dist: cython-lint; extra == "dev"
Dynamic: license-file
